{
  "content": [
    {
      "content": null,
      "created": "2024-07-10T21:44:02.256406Z",
      "format": null,
      "hash": null,
      "hash_algorithm": null,
      "last_modified": "2024-07-10T21:33:25.353356Z",
      "mimetype": "text/javascript",
      "name": "48.edcac641a8a56d6a94af.js",
      "path": "extensions/jupyterlab-jupytext/static/48.edcac641a8a56d6a94af.js",
      "size": 27495,
      "type": "file",
      "writable": true
    },
    {
      "content": null,
      "created": "2024-07-10T21:44:02.256406Z",
      "format": null,
      "hash": null,
      "hash_algorithm": null,
      "last_modified": "2024-07-10T21:33:25.353356Z",
      "mimetype": "text/plain",
      "name": "48.edcac641a8a56d6a94af.js.LICENSE.txt",
      "path": "extensions/jupyterlab-jupytext/static/48.edcac641a8a56d6a94af.js.LICENSE.txt",
      "size": 225,
      "type": "file",
      "writable": true
    },
    {
      "content": null,
      "created": "2024-07-10T21:44:02.256406Z",
      "format": null,
      "hash": null,
      "hash_algorithm": null,
      "last_modified": "2024-07-10T21:33:25.353356Z",
      "mimetype": "application/json",
      "name": "third-party-licenses.json",
      "path": "extensions/jupyterlab-jupytext/static/third-party-licenses.json",
      "size": 4245,
      "type": "file",
      "writable": true
    },
    {
      "content": null,
      "created": "2024-07-10T21:44:02.256406Z",
      "format": null,
      "hash": null,
      "hash_algorithm": null,
      "last_modified": "2024-07-10T21:33:25.353356Z",
      "mimetype": "text/javascript",
      "name": "style.js",
      "path": "extensions/jupyterlab-jupytext/static/style.js",
      "size": 118,
      "type": "file",
      "writable": true
    },
    {
      "content": null,
      "created": "2024-07-10T21:44:02.256406Z",
      "format": null,
      "hash": null,
      "hash_algorithm": null,
      "last_modified": "2024-07-10T21:33:25.353356Z",
      "mimetype": "text/javascript",
      "name": "remoteEntry.a216559d1d4347a62591.js",
      "path": "extensions/jupyterlab-jupytext/static/remoteEntry.a216559d1d4347a62591.js",
      "size": 8769,
      "type": "file",
      "writable": true
    },
    {
      "content": null,
      "created": "2024-07-10T21:44:02.256406Z",
      "format": null,
      "hash": null,
      "hash_algorithm": null,
      "last_modified": "2024-07-10T21:33:25.353356Z",
      "mimetype": "text/javascript",
      "name": "509.5be7091fd087cb192c3f.js",
      "path": "extensions/jupyterlab-jupytext/static/509.5be7091fd087cb192c3f.js",
      "size": 21872,
      "type": "file",
      "writable": true
    },
    {
      "content": null,
      "created": "2024-07-10T21:44:02.256406Z",
      "format": null,
      "hash": null,
      "hash_algorithm": null,
      "last_modified": "2024-07-10T21:33:25.353356Z",
      "mimetype": "text/javascript",
      "name": "720.24d950cc6997b442f018.js",
      "path": "extensions/jupyterlab-jupytext/static/720.24d950cc6997b442f018.js",
      "size": 11055,
      "type": "file",
      "writable": true
    }
  ],
  "created": "2024-07-10T21:44:02.256406Z",
  "format": "json",
  "hash": null,
  "hash_algorithm": null,
  "last_modified": "2024-07-10T21:44:02.256406Z",
  "mimetype": null,
  "name": "static",
  "path": "extensions/jupyterlab-jupytext/static",
  "size": null,
  "type": "directory",
  "writable": true
}