{
  "content": [
    {
      "content": null,
      "created": "2024-07-10T21:44:02.256406Z",
      "format": null,
      "hash": null,
      "hash_algorithm": null,
      "last_modified": "2024-07-10T21:38:35.204890Z",
      "mimetype": "text/javascript",
      "name": "568.1e2faa2ba0bbe59c4780.js",
      "path": "extensions/jupyterlab_pygments/static/568.1e2faa2ba0bbe59c4780.js",
      "size": 224,
      "type": "file",
      "writable": true
    },
    {
      "content": null,
      "created": "2024-07-10T21:44:02.260406Z",
      "format": null,
      "hash": null,
      "hash_algorithm": null,
      "last_modified": "2024-07-10T21:38:35.204890Z",
      "mimetype": "application/json",
      "name": "third-party-licenses.json",
      "path": "extensions/jupyterlab_pygments/static/third-party-licenses.json",
      "size": 2452,
      "type": "file",
      "writable": true
    },
    {
      "content": null,
      "created": "2024-07-10T21:44:02.260406Z",
      "format": null,
      "hash": null,
      "hash_algorithm": null,
      "last_modified": "2024-07-10T21:38:35.204890Z",
      "mimetype": "text/javascript",
      "name": "remoteEntry.5cbb9d2323598fbda535.js",
      "path": "extensions/jupyterlab_pygments/static/remoteEntry.5cbb9d2323598fbda535.js",
      "size": 3925,
      "type": "file",
      "writable": true
    },
    {
      "content": null,
      "created": "2024-07-10T21:44:02.260406Z",
      "format": null,
      "hash": null,
      "hash_algorithm": null,
      "last_modified": "2024-07-10T21:38:35.204890Z",
      "mimetype": "text/javascript",
      "name": "style.js",
      "path": "extensions/jupyterlab_pygments/static/style.js",
      "size": 162,
      "type": "file",
      "writable": true
    },
    {
      "content": null,
      "created": "2024-07-10T21:44:02.260406Z",
      "format": null,
      "hash": null,
      "hash_algorithm": null,
      "last_modified": "2024-07-10T21:38:35.204890Z",
      "mimetype": "text/javascript",
      "name": "747.67662283a5707eeb4d4c.js",
      "path": "extensions/jupyterlab_pygments/static/747.67662283a5707eeb4d4c.js",
      "size": 8351,
      "type": "file",
      "writable": true
    }
  ],
  "created": "2024-07-10T21:44:02.260406Z",
  "format": "json",
  "hash": null,
  "hash_algorithm": null,
  "last_modified": "2024-07-10T21:44:02.260406Z",
  "mimetype": null,
  "name": "static",
  "path": "extensions/jupyterlab_pygments/static",
  "size": null,
  "type": "directory",
  "writable": true
}